{
    "T1": {
        "candTksInfo": [
            {
                "candNo": 1,
                "tks": 18095,
                "candVictor": "*",
                "tksRate": 17.6,
                "name": "\u9ec3\u7d39\u5ead",
                "birthday": "19700111",
                "party": "\u4e2d\u570b\u570b\u6c11\u9ee8"
            },
            {
                "candNo": 2,
                "tks": 12522,
                "candVictor": "*",
                "tksRate": 12.18,
                "name": "\u9673\u82e5\u7fe0",
                "birthday": "19690429",
                "party": "\u4e2d\u570b\u570b\u6c11\u9ee8"
            },
            {
                "candNo": 3,
                "tks": 9166,
                "candVictor": " ",
                "tksRate": 8.92,
                "name": "\u8521\u9d3b\u744b",
                "birthday": "19950304",
                "party": "\u53f0\u7063\u5718\u7d50\u806f\u76df"
            },
            {
                "candNo": 4,
                "tks": 14783,
                "candVictor": "*",
                "tksRate": 14.38,
                "name": "\u8a31\u5d11\u6e90",
                "birthday": "19570501",
                "party": "\u4e2d\u570b\u570b\u6c11\u9ee8"
            },
            {
                "candNo": 5,
                "tks": 13158,
                "candVictor": "*",
                "tksRate": 12.8,
                "name": "\u90ed\u5efa\u76df",
                "birthday": "19700720",
                "party": "\u6c11\u4e3b\u9032\u6b65\u9ee8"
            },
            {
                "candNo": 6,
                "tks": 9365,
                "candVictor": " ",
                "tksRate": 9.11,
                "name": "\u5468\u73b2\u598f",
                "birthday": "19671216",
                "party": "\u6c11\u4e3b\u9032\u6b65\u9ee8"
            },
            {
                "candNo": 7,
                "tks": 14882,
                "candVictor": "*",
                "tksRate": 14.47,
                "name": "\u9ec3\u6587\u76ca",
                "birthday": "19760602",
                "party": "\u6c11\u4e3b\u9032\u6b65\u9ee8"
            },
            {
                "candNo": 8,
                "tks": 350,
                "candVictor": " ",
                "tksRate": 0.34,
                "name": "\u9673\u9298\u745e",
                "birthday": "19590921",
                "party": "\u7121"
            },
            {
                "candNo": 9,
                "tks": 10492,
                "candVictor": "*",
                "tksRate": 10.2,
                "name": "\u5433\u76ca\u653f",
                "birthday": "19630404",
                "party": "\u89aa\u6c11\u9ee8"
            }
        ],
        "totalVotables": 142123,
        "voteRate": 73.96,
        "areaCode": "08",
        "deptCode": "080"
    },
    "T2": {
        "candTksInfo": [
            {
                "candNo": 1,
                "tks": 81,
                "candVictor": " ",
                "tksRate": 50.94,
                "name": "\u4fc4\u9127\uff0e\u6bb7\u827e Eteng\uff0eIngay",
                "birthday": "19650224",
                "party": "\u6c11\u4e3b\u9032\u6b65\u9ee8"
            },
            {
                "candNo": 2,
                "tks": 67,
                "candVictor": "*",
                "tksRate": 42.14,
                "name": "\u738b\u7fa9\u96c4",
                "birthday": "19600320",
                "party": "\u4e2d\u570b\u570b\u6c11\u9ee8"
            },
            {
                "candNo": 3,
                "tks": 11,
                "candVictor": " ",
                "tksRate": 6.92,
                "name": "\u8a79\u91d1\u798f",
                "birthday": "19490408",
                "party": "\u89aa\u6c11\u9ee8"
            }
        ],
        "totalVotables": 251,
        "voteRate": 66.53,
        "areaCode": "12",
        "deptCode": "080"
    },
    "TC": {
        "candTksInfo": [
            {
                "candNo": 1,
                "tks": 57171,
                "candVictor": "*",
                "tksRate": 54.6,
                "name": "\u97d3\u570b\u745c",
                "birthday": "19570617",
                "party": "\u4e2d\u570b\u570b\u6c11\u9ee8"
            },
            {
                "candNo": 2,
                "tks": 46041,
                "candVictor": " ",
                "tksRate": 43.97,
                "name": "\u9673\u5176\u9081",
                "birthday": "19641223",
                "party": "\u6c11\u4e3b\u9032\u6b65\u9ee8"
            },
            {
                "candNo": 3,
                "tks": 401,
                "candVictor": " ",
                "tksRate": 0.38,
                "name": "\u74a9\u7f8e\u9cf3",
                "birthday": "19660805",
                "party": "\u7121"
            },
            {
                "candNo": 4,
                "tks": 1098,
                "candVictor": " ",
                "tksRate": 1.05,
                "name": "\u8607\u76c8\u8cb4",
                "birthday": "19581007",
                "party": "\u7121"
            }
        ],
        "totalVotables": 143124,
        "voteRate": 73.95,
        "areaCode": null,
        "deptCode": "080"
    },
    "T3": {
        "candTksInfo": [
            {
                "candNo": 1,
                "tks": 60,
                "candVictor": " ",
                "tksRate": 46.15,
                "name": "\u8303\u7e54\u6b3d Pasulang\uff0eTomatalate",
                "birthday": "19570729",
                "party": "\u7121"
            },
            {
                "candNo": 2,
                "tks": 70,
                "candVictor": "*",
                "tksRate": 53.85,
                "name": "\u5510\u60e0\u7f8e",
                "birthday": "19580101",
                "party": "\u4e2d\u570b\u570b\u6c11\u9ee8"
            }
        ],
        "totalVotables": 203,
        "voteRate": 67.98,
        "areaCode": "15",
        "deptCode": "080"
    },
    "F6": {
        "agreeTks": 56526,
        "disagreeTks": 31867,
        "totalVotables": 146786,
        "voteRate": 60.22
    },
    "F7": {
        "agreeTks": 43358,
        "disagreeTks": 45565,
        "totalVotables": 146786,
        "voteRate": 60.58
    },
    "F8": {
        "agreeTks": 28522,
        "disagreeTks": 57208,
        "totalVotables": 146786,
        "voteRate": 58.4
    },
    "F9": {
        "agreeTks": 29700,
        "disagreeTks": 55824,
        "totalVotables": 146786,
        "voteRate": 58.26
    },
    "F1": {
        "agreeTks": 62964,
        "disagreeTks": 18917,
        "totalVotables": 146786,
        "voteRate": 55.78
    },
    "FA": {
        "agreeTks": 48433,
        "disagreeTks": 34428,
        "totalVotables": 146786,
        "voteRate": 56.45
    },
    "F2": {
        "agreeTks": 60364,
        "disagreeTks": 21461,
        "totalVotables": 146786,
        "voteRate": 55.74
    },
    "F3": {
        "agreeTks": 62255,
        "disagreeTks": 19545,
        "totalVotables": 146786,
        "voteRate": 55.73
    },
    "F4": {
        "agreeTks": 64689,
        "disagreeTks": 24674,
        "totalVotables": 146786,
        "voteRate": 60.88
    },
    "F5": {
        "agreeTks": 60784,
        "disagreeTks": 27867,
        "totalVotables": 146786,
        "voteRate": 60.39
    },
    "age": [
        8020,
        10159,
        10990,
        11972,
        13902,
        12963,
        12436,
        12622,
        13941,
        14252,
        12481,
        7010,
        5541,
        3322,
        1835,
        763,
        177,
        17
    ],
    "education": [
        18237,
        19870,
        46687,
        17759,
        38019,
        10791,
        1040
    ],
    "sex": [
        72712,
        79691
    ],
    "merriage": [
        54376,
        72960,
        14465,
        10602
    ],
    "middle_num": 625
}