{
    "001": {
        "T1": {
            "candTksInfo": [
                {
                    "candNo": 1,
                    "tks": 70,
                    "candVictor": " ",
                    "tksRate": 6.84,
                    "name": "\u8521\u7950\u660c",
                    "birthday": "19700112",
                    "party": "\u7121"
                },
                {
                    "candNo": 2,
                    "tks": 122,
                    "candVictor": " ",
                    "tksRate": 11.91,
                    "name": "\u9673\u798f\u6176",
                    "birthday": "19520625",
                    "party": "\u7121"
                },
                {
                    "candNo": 3,
                    "tks": 266,
                    "candVictor": " ",
                    "tksRate": 25.98,
                    "name": "\u738b\u958b\u73b9",
                    "birthday": "19820312",
                    "party": "\u6c11\u4e3b\u9032\u6b65\u9ee8"
                },
                {
                    "candNo": 4,
                    "tks": 566,
                    "candVictor": "*",
                    "tksRate": 55.27,
                    "name": "\u5468\u5955\u9f4a",
                    "birthday": "19881228",
                    "party": "\u7121"
                }
            ],
            "totalVotables": 1347,
            "voteRate": 78.1,
            "areaCode": "04",
            "deptCode": "250"
        },
        "T2": {
            "candTksInfo": [
                {
                    "candNo": 1,
                    "tks": 1,
                    "candVictor": "*",
                    "tksRate": 100.0,
                    "name": "\u7a4e\u827e\u9054\u5229 Ingay Tali",
                    "birthday": "19730306",
                    "party": "\u7121"
                },
                {
                    "candNo": 2,
                    "tks": 0,
                    "candVictor": " ",
                    "tksRate": 0.0,
                    "name": "\u7c21\u5fb7\u8f1d",
                    "birthday": "19610102",
                    "party": "\u4e2d\u570b\u570b\u6c11\u9ee8"
                },
                {
                    "candNo": 3,
                    "tks": 0,
                    "candVictor": " ",
                    "tksRate": 0.0,
                    "name": "\u674e\u7f8e\u7d20",
                    "birthday": "19690721",
                    "party": "\u6c11\u4e3b\u9032\u6b65\u9ee8"
                }
            ],
            "totalVotables": 1,
            "voteRate": 100.0,
            "areaCode": "12",
            "deptCode": "250"
        },
        "TC": {
            "candTksInfo": [
                {
                    "candNo": 1,
                    "tks": 362,
                    "candVictor": "*",
                    "tksRate": 35.21,
                    "name": "\u9ec3\u5049\u54f2",
                    "birthday": "19630926",
                    "party": "\u6c11\u4e3b\u9032\u6b65\u9ee8"
                },
                {
                    "candNo": 2,
                    "tks": 411,
                    "candVictor": " ",
                    "tksRate": 39.98,
                    "name": "\u9ad8\u601d\u535a",
                    "birthday": "19681031",
                    "party": "\u4e2d\u570b\u570b\u6c11\u9ee8"
                },
                {
                    "candNo": 3,
                    "tks": 74,
                    "candVictor": " ",
                    "tksRate": 7.2,
                    "name": "\u6797\u7fa9\u8c50",
                    "birthday": "19480204",
                    "party": "\u7121"
                },
                {
                    "candNo": 4,
                    "tks": 32,
                    "candVictor": " ",
                    "tksRate": 3.11,
                    "name": "\u8a31\u5fe0\u4fe1",
                    "birthday": "19650601",
                    "party": "\u7121"
                },
                {
                    "candNo": 5,
                    "tks": 90,
                    "candVictor": " ",
                    "tksRate": 8.75,
                    "name": "\u9673\u6c38\u548c",
                    "birthday": "19600216",
                    "party": "\u7121"
                },
                {
                    "candNo": 6,
                    "tks": 59,
                    "candVictor": " ",
                    "tksRate": 5.74,
                    "name": "\u8607\u7165\u667a",
                    "birthday": "19560720",
                    "party": "\u7121"
                }
            ],
            "totalVotables": 1353,
            "voteRate": 78.05,
            "areaCode": null,
            "deptCode": "250"
        },
        "T3": {
            "candTksInfo": [
                {
                    "candNo": 1,
                    "tks": 0,
                    "candVictor": " ",
                    "tksRate": 0.0,
                    "name": "\u4f0d\u5b97\u5eb7",
                    "birthday": "19780723",
                    "party": "\u4e2d\u570b\u570b\u6c11\u9ee8"
                },
                {
                    "candNo": 2,
                    "tks": 2,
                    "candVictor": "*",
                    "tksRate": 100.0,
                    "name": "\u8c37\u66ae\u2027\u54c8\u5c31Kumu\u2027Hacyo",
                    "birthday": "19780528",
                    "party": "\u7121"
                }
            ],
            "totalVotables": 3,
            "voteRate": 66.67,
            "areaCode": "13",
            "deptCode": "250"
        },
        "F6": {
            "agreeTks": 374,
            "disagreeTks": 302,
            "totalVotables": 1385,
            "voteRate": 48.81
        },
        "F7": {
            "agreeTks": 362,
            "disagreeTks": 362,
            "totalVotables": 1385,
            "voteRate": 52.27
        },
        "F8": {
            "agreeTks": 215,
            "disagreeTks": 451,
            "totalVotables": 1385,
            "voteRate": 48.09
        },
        "F9": {
            "agreeTks": 243,
            "disagreeTks": 437,
            "totalVotables": 1385,
            "voteRate": 49.1
        },
        "F1": {
            "agreeTks": 504,
            "disagreeTks": 148,
            "totalVotables": 1385,
            "voteRate": 47.08
        },
        "FA": {
            "agreeTks": 359,
            "disagreeTks": 292,
            "totalVotables": 1385,
            "voteRate": 47.0
        },
        "F2": {
            "agreeTks": 478,
            "disagreeTks": 164,
            "totalVotables": 1385,
            "voteRate": 46.35
        },
        "F3": {
            "agreeTks": 476,
            "disagreeTks": 169,
            "totalVotables": 1385,
            "voteRate": 46.57
        },
        "F4": {
            "agreeTks": 525,
            "disagreeTks": 182,
            "totalVotables": 1385,
            "voteRate": 51.05
        },
        "F5": {
            "agreeTks": 454,
            "disagreeTks": 233,
            "totalVotables": 1385,
            "voteRate": 49.6
        },
        "age": [
            57,
            89,
            103,
            106,
            88,
            110,
            101,
            139,
            140,
            137,
            131,
            74,
            54,
            58,
            28,
            13,
            4,
            0
        ],
        "education": [
            368,
            295,
            416,
            94,
            229,
            30,
            0
        ],
        "sex": [
            762,
            670
        ],
        "merriage": [
            408,
            734,
            140,
            150
        ],
        "middle_num": 540
    },
    "002": {
        "T1": {
            "candTksInfo": [
                {
                    "candNo": 1,
                    "tks": 49,
                    "candVictor": " ",
                    "tksRate": 9.94,
                    "name": "\u8521\u7950\u660c",
                    "birthday": "19700112",
                    "party": "\u7121"
                },
                {
                    "candNo": 2,
                    "tks": 59,
                    "candVictor": " ",
                    "tksRate": 11.97,
                    "name": "\u9673\u798f\u6176",
                    "birthday": "19520625",
                    "party": "\u7121"
                },
                {
                    "candNo": 3,
                    "tks": 117,
                    "candVictor": " ",
                    "tksRate": 23.73,
                    "name": "\u738b\u958b\u73b9",
                    "birthday": "19820312",
                    "party": "\u6c11\u4e3b\u9032\u6b65\u9ee8"
                },
                {
                    "candNo": 4,
                    "tks": 268,
                    "candVictor": "*",
                    "tksRate": 54.36,
                    "name": "\u5468\u5955\u9f4a",
                    "birthday": "19881228",
                    "party": "\u7121"
                }
            ],
            "totalVotables": 776,
            "voteRate": 64.69,
            "areaCode": "04",
            "deptCode": "250"
        },
        "T2": {
            "candTksInfo": [
                {
                    "candNo": 1,
                    "tks": 0,
                    "candVictor": "*",
                    "tksRate": 0.0,
                    "name": "\u7a4e\u827e\u9054\u5229 Ingay Tali",
                    "birthday": "19730306",
                    "party": "\u7121"
                },
                {
                    "candNo": 2,
                    "tks": 0,
                    "candVictor": " ",
                    "tksRate": 0.0,
                    "name": "\u7c21\u5fb7\u8f1d",
                    "birthday": "19610102",
                    "party": "\u4e2d\u570b\u570b\u6c11\u9ee8"
                },
                {
                    "candNo": 3,
                    "tks": 0,
                    "candVictor": " ",
                    "tksRate": 0.0,
                    "name": "\u674e\u7f8e\u7d20",
                    "birthday": "19690721",
                    "party": "\u6c11\u4e3b\u9032\u6b65\u9ee8"
                }
            ],
            "totalVotables": 0,
            "voteRate": 0.0,
            "areaCode": "12",
            "deptCode": "250"
        },
        "TC": {
            "candTksInfo": [
                {
                    "candNo": 1,
                    "tks": 145,
                    "candVictor": "*",
                    "tksRate": 29.53,
                    "name": "\u9ec3\u5049\u54f2",
                    "birthday": "19630926",
                    "party": "\u6c11\u4e3b\u9032\u6b65\u9ee8"
                },
                {
                    "candNo": 2,
                    "tks": 219,
                    "candVictor": " ",
                    "tksRate": 44.6,
                    "name": "\u9ad8\u601d\u535a",
                    "birthday": "19681031",
                    "party": "\u4e2d\u570b\u570b\u6c11\u9ee8"
                },
                {
                    "candNo": 3,
                    "tks": 53,
                    "candVictor": " ",
                    "tksRate": 10.79,
                    "name": "\u6797\u7fa9\u8c50",
                    "birthday": "19480204",
                    "party": "\u7121"
                },
                {
                    "candNo": 4,
                    "tks": 11,
                    "candVictor": " ",
                    "tksRate": 2.24,
                    "name": "\u8a31\u5fe0\u4fe1",
                    "birthday": "19650601",
                    "party": "\u7121"
                },
                {
                    "candNo": 5,
                    "tks": 27,
                    "candVictor": " ",
                    "tksRate": 5.5,
                    "name": "\u9673\u6c38\u548c",
                    "birthday": "19600216",
                    "party": "\u7121"
                },
                {
                    "candNo": 6,
                    "tks": 36,
                    "candVictor": " ",
                    "tksRate": 7.33,
                    "name": "\u8607\u7165\u667a",
                    "birthday": "19560720",
                    "party": "\u7121"
                }
            ],
            "totalVotables": 776,
            "voteRate": 64.69,
            "areaCode": null,
            "deptCode": "250"
        },
        "T3": {
            "candTksInfo": [
                {
                    "candNo": 1,
                    "tks": 0,
                    "candVictor": " ",
                    "tksRate": 0.0,
                    "name": "\u4f0d\u5b97\u5eb7",
                    "birthday": "19780723",
                    "party": "\u4e2d\u570b\u570b\u6c11\u9ee8"
                },
                {
                    "candNo": 2,
                    "tks": 0,
                    "candVictor": "*",
                    "tksRate": 0.0,
                    "name": "\u8c37\u66ae\u2027\u54c8\u5c31Kumu\u2027Hacyo",
                    "birthday": "19780528",
                    "party": "\u7121"
                }
            ],
            "totalVotables": 0,
            "voteRate": 0.0,
            "areaCode": "13",
            "deptCode": "250"
        },
        "F6": {
            "agreeTks": 181,
            "disagreeTks": 146,
            "totalVotables": 806,
            "voteRate": 45.29
        },
        "F7": {
            "agreeTks": 165,
            "disagreeTks": 163,
            "totalVotables": 806,
            "voteRate": 45.53
        },
        "F8": {
            "agreeTks": 84,
            "disagreeTks": 246,
            "totalVotables": 806,
            "voteRate": 44.91
        },
        "F9": {
            "agreeTks": 93,
            "disagreeTks": 228,
            "totalVotables": 806,
            "voteRate": 44.42
        },
        "F1": {
            "agreeTks": 248,
            "disagreeTks": 71,
            "totalVotables": 806,
            "voteRate": 44.42
        },
        "FA": {
            "agreeTks": 174,
            "disagreeTks": 135,
            "totalVotables": 806,
            "voteRate": 44.54
        },
        "F2": {
            "agreeTks": 236,
            "disagreeTks": 83,
            "totalVotables": 806,
            "voteRate": 44.17
        },
        "F3": {
            "agreeTks": 231,
            "disagreeTks": 87,
            "totalVotables": 806,
            "voteRate": 44.17
        },
        "F4": {
            "agreeTks": 272,
            "disagreeTks": 73,
            "totalVotables": 806,
            "voteRate": 45.53
        },
        "F5": {
            "agreeTks": 223,
            "disagreeTks": 105,
            "totalVotables": 806,
            "voteRate": 45.04
        },
        "age": [
            46,
            47,
            65,
            54,
            69,
            54,
            57,
            78,
            87,
            81,
            57,
            45,
            24,
            30,
            26,
            4,
            0,
            0
        ],
        "education": [
            253,
            204,
            212,
            52,
            96,
            6,
            1
        ],
        "sex": [
            472,
            352
        ],
        "merriage": [
            233,
            450,
            55,
            86
        ],
        "middle_num": 516
    },
    "005": {
        "T1": {
            "candTksInfo": [
                {
                    "candNo": 1,
                    "tks": 26,
                    "candVictor": " ",
                    "tksRate": 6.67,
                    "name": "\u8521\u7950\u660c",
                    "birthday": "19700112",
                    "party": "\u7121"
                },
                {
                    "candNo": 2,
                    "tks": 35,
                    "candVictor": " ",
                    "tksRate": 8.97,
                    "name": "\u9673\u798f\u6176",
                    "birthday": "19520625",
                    "party": "\u7121"
                },
                {
                    "candNo": 3,
                    "tks": 120,
                    "candVictor": " ",
                    "tksRate": 30.77,
                    "name": "\u738b\u958b\u73b9",
                    "birthday": "19820312",
                    "party": "\u6c11\u4e3b\u9032\u6b65\u9ee8"
                },
                {
                    "candNo": 4,
                    "tks": 209,
                    "candVictor": "*",
                    "tksRate": 53.59,
                    "name": "\u5468\u5955\u9f4a",
                    "birthday": "19881228",
                    "party": "\u7121"
                }
            ],
            "totalVotables": 639,
            "voteRate": 62.91,
            "areaCode": "04",
            "deptCode": "250"
        },
        "T2": {
            "candTksInfo": [
                {
                    "candNo": 1,
                    "tks": 0,
                    "candVictor": "*",
                    "tksRate": 0.0,
                    "name": "\u7a4e\u827e\u9054\u5229 Ingay Tali",
                    "birthday": "19730306",
                    "party": "\u7121"
                },
                {
                    "candNo": 2,
                    "tks": 0,
                    "candVictor": " ",
                    "tksRate": 0.0,
                    "name": "\u7c21\u5fb7\u8f1d",
                    "birthday": "19610102",
                    "party": "\u4e2d\u570b\u570b\u6c11\u9ee8"
                },
                {
                    "candNo": 3,
                    "tks": 0,
                    "candVictor": " ",
                    "tksRate": 0.0,
                    "name": "\u674e\u7f8e\u7d20",
                    "birthday": "19690721",
                    "party": "\u6c11\u4e3b\u9032\u6b65\u9ee8"
                }
            ],
            "totalVotables": 0,
            "voteRate": 0.0,
            "areaCode": "12",
            "deptCode": "250"
        },
        "TC": {
            "candTksInfo": [
                {
                    "candNo": 1,
                    "tks": 126,
                    "candVictor": "*",
                    "tksRate": 31.98,
                    "name": "\u9ec3\u5049\u54f2",
                    "birthday": "19630926",
                    "party": "\u6c11\u4e3b\u9032\u6b65\u9ee8"
                },
                {
                    "candNo": 2,
                    "tks": 169,
                    "candVictor": " ",
                    "tksRate": 42.89,
                    "name": "\u9ad8\u601d\u535a",
                    "birthday": "19681031",
                    "party": "\u4e2d\u570b\u570b\u6c11\u9ee8"
                },
                {
                    "candNo": 3,
                    "tks": 36,
                    "candVictor": " ",
                    "tksRate": 9.14,
                    "name": "\u6797\u7fa9\u8c50",
                    "birthday": "19480204",
                    "party": "\u7121"
                },
                {
                    "candNo": 4,
                    "tks": 18,
                    "candVictor": " ",
                    "tksRate": 4.57,
                    "name": "\u8a31\u5fe0\u4fe1",
                    "birthday": "19650601",
                    "party": "\u7121"
                },
                {
                    "candNo": 5,
                    "tks": 28,
                    "candVictor": " ",
                    "tksRate": 7.11,
                    "name": "\u9673\u6c38\u548c",
                    "birthday": "19600216",
                    "party": "\u7121"
                },
                {
                    "candNo": 6,
                    "tks": 17,
                    "candVictor": " ",
                    "tksRate": 4.31,
                    "name": "\u8607\u7165\u667a",
                    "birthday": "19560720",
                    "party": "\u7121"
                }
            ],
            "totalVotables": 642,
            "voteRate": 62.62,
            "areaCode": null,
            "deptCode": "250"
        },
        "T3": {
            "candTksInfo": [
                {
                    "candNo": 1,
                    "tks": 0,
                    "candVictor": " ",
                    "tksRate": 0.0,
                    "name": "\u4f0d\u5b97\u5eb7",
                    "birthday": "19780723",
                    "party": "\u4e2d\u570b\u570b\u6c11\u9ee8"
                },
                {
                    "candNo": 2,
                    "tks": 0,
                    "candVictor": "*",
                    "tksRate": 0.0,
                    "name": "\u8c37\u66ae\u2027\u54c8\u5c31Kumu\u2027Hacyo",
                    "birthday": "19780528",
                    "party": "\u7121"
                }
            ],
            "totalVotables": 0,
            "voteRate": 0.0,
            "areaCode": "13",
            "deptCode": "250"
        },
        "F6": {
            "agreeTks": 142,
            "disagreeTks": 104,
            "totalVotables": 654,
            "voteRate": 41.74
        },
        "F7": {
            "agreeTks": 118,
            "disagreeTks": 127,
            "totalVotables": 654,
            "voteRate": 41.59
        },
        "F8": {
            "agreeTks": 53,
            "disagreeTks": 188,
            "totalVotables": 654,
            "voteRate": 41.44
        },
        "F9": {
            "agreeTks": 65,
            "disagreeTks": 168,
            "totalVotables": 654,
            "voteRate": 41.59
        },
        "F1": {
            "agreeTks": 191,
            "disagreeTks": 38,
            "totalVotables": 654,
            "voteRate": 41.13
        },
        "FA": {
            "agreeTks": 138,
            "disagreeTks": 86,
            "totalVotables": 654,
            "voteRate": 41.28
        },
        "F2": {
            "agreeTks": 177,
            "disagreeTks": 48,
            "totalVotables": 654,
            "voteRate": 41.13
        },
        "F3": {
            "agreeTks": 168,
            "disagreeTks": 53,
            "totalVotables": 654,
            "voteRate": 41.13
        },
        "F4": {
            "agreeTks": 192,
            "disagreeTks": 51,
            "totalVotables": 654,
            "voteRate": 41.59
        },
        "F5": {
            "agreeTks": 173,
            "disagreeTks": 64,
            "totalVotables": 654,
            "voteRate": 41.59
        },
        "age": [
            25,
            52,
            45,
            32,
            48,
            46,
            53,
            62,
            67,
            70,
            56,
            35,
            38,
            22,
            17,
            4,
            0,
            0
        ],
        "education": [
            202,
            186,
            159,
            29,
            87,
            7,
            2
        ],
        "sex": [
            374,
            298
        ],
        "merriage": [
            163,
            377,
            61,
            71
        ],
        "middle_num": 511
    },
    "006": {
        "T1": {
            "candTksInfo": [
                {
                    "candNo": 1,
                    "tks": 31,
                    "candVictor": " ",
                    "tksRate": 6.86,
                    "name": "\u8521\u7950\u660c",
                    "birthday": "19700112",
                    "party": "\u7121"
                },
                {
                    "candNo": 2,
                    "tks": 101,
                    "candVictor": " ",
                    "tksRate": 22.35,
                    "name": "\u9673\u798f\u6176",
                    "birthday": "19520625",
                    "party": "\u7121"
                },
                {
                    "candNo": 3,
                    "tks": 141,
                    "candVictor": " ",
                    "tksRate": 31.19,
                    "name": "\u738b\u958b\u73b9",
                    "birthday": "19820312",
                    "party": "\u6c11\u4e3b\u9032\u6b65\u9ee8"
                },
                {
                    "candNo": 4,
                    "tks": 179,
                    "candVictor": "*",
                    "tksRate": 39.6,
                    "name": "\u5468\u5955\u9f4a",
                    "birthday": "19881228",
                    "party": "\u7121"
                }
            ],
            "totalVotables": 762,
            "voteRate": 60.76,
            "areaCode": "04",
            "deptCode": "250"
        },
        "T2": {
            "candTksInfo": [
                {
                    "candNo": 1,
                    "tks": 0,
                    "candVictor": "*",
                    "tksRate": 0.0,
                    "name": "\u7a4e\u827e\u9054\u5229 Ingay Tali",
                    "birthday": "19730306",
                    "party": "\u7121"
                },
                {
                    "candNo": 2,
                    "tks": 0,
                    "candVictor": " ",
                    "tksRate": 0.0,
                    "name": "\u7c21\u5fb7\u8f1d",
                    "birthday": "19610102",
                    "party": "\u4e2d\u570b\u570b\u6c11\u9ee8"
                },
                {
                    "candNo": 3,
                    "tks": 0,
                    "candVictor": " ",
                    "tksRate": 0.0,
                    "name": "\u674e\u7f8e\u7d20",
                    "birthday": "19690721",
                    "party": "\u6c11\u4e3b\u9032\u6b65\u9ee8"
                }
            ],
            "totalVotables": 0,
            "voteRate": 0.0,
            "areaCode": "12",
            "deptCode": "250"
        },
        "TC": {
            "candTksInfo": [
                {
                    "candNo": 1,
                    "tks": 173,
                    "candVictor": "*",
                    "tksRate": 37.94,
                    "name": "\u9ec3\u5049\u54f2",
                    "birthday": "19630926",
                    "party": "\u6c11\u4e3b\u9032\u6b65\u9ee8"
                },
                {
                    "candNo": 2,
                    "tks": 178,
                    "candVictor": " ",
                    "tksRate": 39.04,
                    "name": "\u9ad8\u601d\u535a",
                    "birthday": "19681031",
                    "party": "\u4e2d\u570b\u570b\u6c11\u9ee8"
                },
                {
                    "candNo": 3,
                    "tks": 34,
                    "candVictor": " ",
                    "tksRate": 7.46,
                    "name": "\u6797\u7fa9\u8c50",
                    "birthday": "19480204",
                    "party": "\u7121"
                },
                {
                    "candNo": 4,
                    "tks": 19,
                    "candVictor": " ",
                    "tksRate": 4.17,
                    "name": "\u8a31\u5fe0\u4fe1",
                    "birthday": "19650601",
                    "party": "\u7121"
                },
                {
                    "candNo": 5,
                    "tks": 40,
                    "candVictor": " ",
                    "tksRate": 8.77,
                    "name": "\u9673\u6c38\u548c",
                    "birthday": "19600216",
                    "party": "\u7121"
                },
                {
                    "candNo": 6,
                    "tks": 12,
                    "candVictor": " ",
                    "tksRate": 2.63,
                    "name": "\u8607\u7165\u667a",
                    "birthday": "19560720",
                    "party": "\u7121"
                }
            ],
            "totalVotables": 763,
            "voteRate": 60.94,
            "areaCode": null,
            "deptCode": "250"
        },
        "T3": {
            "candTksInfo": [
                {
                    "candNo": 1,
                    "tks": 0,
                    "candVictor": " ",
                    "tksRate": 0.0,
                    "name": "\u4f0d\u5b97\u5eb7",
                    "birthday": "19780723",
                    "party": "\u4e2d\u570b\u570b\u6c11\u9ee8"
                },
                {
                    "candNo": 2,
                    "tks": 0,
                    "candVictor": "*",
                    "tksRate": 0.0,
                    "name": "\u8c37\u66ae\u2027\u54c8\u5c31Kumu\u2027Hacyo",
                    "birthday": "19780528",
                    "party": "\u7121"
                }
            ],
            "totalVotables": 0,
            "voteRate": 0.0,
            "areaCode": "13",
            "deptCode": "250"
        },
        "F6": {
            "agreeTks": 150,
            "disagreeTks": 99,
            "totalVotables": 783,
            "voteRate": 36.4
        },
        "F7": {
            "agreeTks": 142,
            "disagreeTks": 124,
            "totalVotables": 783,
            "voteRate": 36.65
        },
        "F8": {
            "agreeTks": 81,
            "disagreeTks": 169,
            "totalVotables": 783,
            "voteRate": 36.4
        },
        "F9": {
            "agreeTks": 97,
            "disagreeTks": 154,
            "totalVotables": 783,
            "voteRate": 36.27
        },
        "F1": {
            "agreeTks": 198,
            "disagreeTks": 53,
            "totalVotables": 783,
            "voteRate": 36.02
        },
        "FA": {
            "agreeTks": 139,
            "disagreeTks": 107,
            "totalVotables": 783,
            "voteRate": 36.02
        },
        "F2": {
            "agreeTks": 187,
            "disagreeTks": 56,
            "totalVotables": 783,
            "voteRate": 36.02
        },
        "F3": {
            "agreeTks": 186,
            "disagreeTks": 65,
            "totalVotables": 783,
            "voteRate": 36.27
        },
        "F4": {
            "agreeTks": 211,
            "disagreeTks": 50,
            "totalVotables": 783,
            "voteRate": 36.4
        },
        "F5": {
            "agreeTks": 178,
            "disagreeTks": 76,
            "totalVotables": 783,
            "voteRate": 36.4
        },
        "age": [
            34,
            49,
            64,
            56,
            48,
            61,
            45,
            85,
            94,
            75,
            58,
            35,
            32,
            44,
            30,
            8,
            0,
            0
        ],
        "education": [
            258,
            195,
            200,
            44,
            105,
            14,
            2
        ],
        "sex": [
            459,
            359
        ],
        "merriage": [
            247,
            408,
            62,
            101
        ],
        "middle_num": 472
    },
    "003": {
        "T1": {
            "candTksInfo": [
                {
                    "candNo": 1,
                    "tks": 26,
                    "candVictor": " ",
                    "tksRate": 7.65,
                    "name": "\u8521\u7950\u660c",
                    "birthday": "19700112",
                    "party": "\u7121"
                },
                {
                    "candNo": 2,
                    "tks": 47,
                    "candVictor": " ",
                    "tksRate": 13.82,
                    "name": "\u9673\u798f\u6176",
                    "birthday": "19520625",
                    "party": "\u7121"
                },
                {
                    "candNo": 3,
                    "tks": 83,
                    "candVictor": " ",
                    "tksRate": 24.41,
                    "name": "\u738b\u958b\u73b9",
                    "birthday": "19820312",
                    "party": "\u6c11\u4e3b\u9032\u6b65\u9ee8"
                },
                {
                    "candNo": 4,
                    "tks": 184,
                    "candVictor": "*",
                    "tksRate": 54.12,
                    "name": "\u5468\u5955\u9f4a",
                    "birthday": "19881228",
                    "party": "\u7121"
                }
            ],
            "totalVotables": 414,
            "voteRate": 84.54,
            "areaCode": "04",
            "deptCode": "250"
        },
        "T2": {
            "candTksInfo": [
                {
                    "candNo": 1,
                    "tks": 0,
                    "candVictor": "*",
                    "tksRate": 0.0,
                    "name": "\u7a4e\u827e\u9054\u5229 Ingay Tali",
                    "birthday": "19730306",
                    "party": "\u7121"
                },
                {
                    "candNo": 2,
                    "tks": 0,
                    "candVictor": " ",
                    "tksRate": 0.0,
                    "name": "\u7c21\u5fb7\u8f1d",
                    "birthday": "19610102",
                    "party": "\u4e2d\u570b\u570b\u6c11\u9ee8"
                },
                {
                    "candNo": 3,
                    "tks": 0,
                    "candVictor": " ",
                    "tksRate": 0.0,
                    "name": "\u674e\u7f8e\u7d20",
                    "birthday": "19690721",
                    "party": "\u6c11\u4e3b\u9032\u6b65\u9ee8"
                }
            ],
            "totalVotables": 0,
            "voteRate": 0.0,
            "areaCode": "12",
            "deptCode": "250"
        },
        "TC": {
            "candTksInfo": [
                {
                    "candNo": 1,
                    "tks": 130,
                    "candVictor": "*",
                    "tksRate": 37.79,
                    "name": "\u9ec3\u5049\u54f2",
                    "birthday": "19630926",
                    "party": "\u6c11\u4e3b\u9032\u6b65\u9ee8"
                },
                {
                    "candNo": 2,
                    "tks": 138,
                    "candVictor": " ",
                    "tksRate": 40.12,
                    "name": "\u9ad8\u601d\u535a",
                    "birthday": "19681031",
                    "party": "\u4e2d\u570b\u570b\u6c11\u9ee8"
                },
                {
                    "candNo": 3,
                    "tks": 23,
                    "candVictor": " ",
                    "tksRate": 6.69,
                    "name": "\u6797\u7fa9\u8c50",
                    "birthday": "19480204",
                    "party": "\u7121"
                },
                {
                    "candNo": 4,
                    "tks": 12,
                    "candVictor": " ",
                    "tksRate": 3.49,
                    "name": "\u8a31\u5fe0\u4fe1",
                    "birthday": "19650601",
                    "party": "\u7121"
                },
                {
                    "candNo": 5,
                    "tks": 23,
                    "candVictor": " ",
                    "tksRate": 6.69,
                    "name": "\u9673\u6c38\u548c",
                    "birthday": "19600216",
                    "party": "\u7121"
                },
                {
                    "candNo": 6,
                    "tks": 18,
                    "candVictor": " ",
                    "tksRate": 5.23,
                    "name": "\u8607\u7165\u667a",
                    "birthday": "19560720",
                    "party": "\u7121"
                }
            ],
            "totalVotables": 416,
            "voteRate": 84.38,
            "areaCode": null,
            "deptCode": "250"
        },
        "T3": {
            "candTksInfo": [
                {
                    "candNo": 1,
                    "tks": 0,
                    "candVictor": " ",
                    "tksRate": 0.0,
                    "name": "\u4f0d\u5b97\u5eb7",
                    "birthday": "19780723",
                    "party": "\u4e2d\u570b\u570b\u6c11\u9ee8"
                },
                {
                    "candNo": 2,
                    "tks": 0,
                    "candVictor": "*",
                    "tksRate": 0.0,
                    "name": "\u8c37\u66ae\u2027\u54c8\u5c31Kumu\u2027Hacyo",
                    "birthday": "19780528",
                    "party": "\u7121"
                }
            ],
            "totalVotables": 0,
            "voteRate": 0.0,
            "areaCode": "13",
            "deptCode": "250"
        },
        "F6": {
            "agreeTks": 129,
            "disagreeTks": 68,
            "totalVotables": 425,
            "voteRate": 48.94
        },
        "F7": {
            "agreeTks": 100,
            "disagreeTks": 94,
            "totalVotables": 425,
            "voteRate": 48.71
        },
        "F8": {
            "agreeTks": 59,
            "disagreeTks": 137,
            "totalVotables": 425,
            "voteRate": 48.47
        },
        "F9": {
            "agreeTks": 56,
            "disagreeTks": 136,
            "totalVotables": 425,
            "voteRate": 48.24
        },
        "F1": {
            "agreeTks": 135,
            "disagreeTks": 48,
            "totalVotables": 425,
            "voteRate": 48.24
        },
        "FA": {
            "agreeTks": 112,
            "disagreeTks": 74,
            "totalVotables": 425,
            "voteRate": 48.71
        },
        "F2": {
            "agreeTks": 132,
            "disagreeTks": 51,
            "totalVotables": 425,
            "voteRate": 48.24
        },
        "F3": {
            "agreeTks": 127,
            "disagreeTks": 58,
            "totalVotables": 425,
            "voteRate": 48.24
        },
        "F4": {
            "agreeTks": 154,
            "disagreeTks": 45,
            "totalVotables": 425,
            "voteRate": 48.94
        },
        "F5": {
            "agreeTks": 145,
            "disagreeTks": 51,
            "totalVotables": 425,
            "voteRate": 48.94
        },
        "age": [
            17,
            22,
            23,
            21,
            26,
            31,
            28,
            34,
            54,
            40,
            38,
            20,
            17,
            30,
            27,
            5,
            2,
            0
        ],
        "education": [
            149,
            110,
            114,
            18,
            40,
            4,
            0
        ],
        "sex": [
            247,
            188
        ],
        "merriage": [
            104,
            247,
            31,
            53
        ],
        "middle_num": 569
    },
    "004": {
        "T1": {
            "candTksInfo": [
                {
                    "candNo": 1,
                    "tks": 18,
                    "candVictor": " ",
                    "tksRate": 4.57,
                    "name": "\u8521\u7950\u660c",
                    "birthday": "19700112",
                    "party": "\u7121"
                },
                {
                    "candNo": 2,
                    "tks": 42,
                    "candVictor": " ",
                    "tksRate": 10.66,
                    "name": "\u9673\u798f\u6176",
                    "birthday": "19520625",
                    "party": "\u7121"
                },
                {
                    "candNo": 3,
                    "tks": 83,
                    "candVictor": " ",
                    "tksRate": 21.07,
                    "name": "\u738b\u958b\u73b9",
                    "birthday": "19820312",
                    "party": "\u6c11\u4e3b\u9032\u6b65\u9ee8"
                },
                {
                    "candNo": 4,
                    "tks": 251,
                    "candVictor": "*",
                    "tksRate": 63.71,
                    "name": "\u5468\u5955\u9f4a",
                    "birthday": "19881228",
                    "party": "\u7121"
                }
            ],
            "totalVotables": 542,
            "voteRate": 73.8,
            "areaCode": "04",
            "deptCode": "250"
        },
        "T2": {
            "candTksInfo": [
                {
                    "candNo": 1,
                    "tks": 0,
                    "candVictor": "*",
                    "tksRate": 0.0,
                    "name": "\u7a4e\u827e\u9054\u5229 Ingay Tali",
                    "birthday": "19730306",
                    "party": "\u7121"
                },
                {
                    "candNo": 2,
                    "tks": 0,
                    "candVictor": " ",
                    "tksRate": 0.0,
                    "name": "\u7c21\u5fb7\u8f1d",
                    "birthday": "19610102",
                    "party": "\u4e2d\u570b\u570b\u6c11\u9ee8"
                },
                {
                    "candNo": 3,
                    "tks": 0,
                    "candVictor": " ",
                    "tksRate": 0.0,
                    "name": "\u674e\u7f8e\u7d20",
                    "birthday": "19690721",
                    "party": "\u6c11\u4e3b\u9032\u6b65\u9ee8"
                }
            ],
            "totalVotables": 0,
            "voteRate": 0.0,
            "areaCode": "12",
            "deptCode": "250"
        },
        "TC": {
            "candTksInfo": [
                {
                    "candNo": 1,
                    "tks": 157,
                    "candVictor": "*",
                    "tksRate": 39.75,
                    "name": "\u9ec3\u5049\u54f2",
                    "birthday": "19630926",
                    "party": "\u6c11\u4e3b\u9032\u6b65\u9ee8"
                },
                {
                    "candNo": 2,
                    "tks": 141,
                    "candVictor": " ",
                    "tksRate": 35.7,
                    "name": "\u9ad8\u601d\u535a",
                    "birthday": "19681031",
                    "party": "\u4e2d\u570b\u570b\u6c11\u9ee8"
                },
                {
                    "candNo": 3,
                    "tks": 37,
                    "candVictor": " ",
                    "tksRate": 9.37,
                    "name": "\u6797\u7fa9\u8c50",
                    "birthday": "19480204",
                    "party": "\u7121"
                },
                {
                    "candNo": 4,
                    "tks": 14,
                    "candVictor": " ",
                    "tksRate": 3.54,
                    "name": "\u8a31\u5fe0\u4fe1",
                    "birthday": "19650601",
                    "party": "\u7121"
                },
                {
                    "candNo": 5,
                    "tks": 26,
                    "candVictor": " ",
                    "tksRate": 6.58,
                    "name": "\u9673\u6c38\u548c",
                    "birthday": "19600216",
                    "party": "\u7121"
                },
                {
                    "candNo": 6,
                    "tks": 20,
                    "candVictor": " ",
                    "tksRate": 5.06,
                    "name": "\u8607\u7165\u667a",
                    "birthday": "19560720",
                    "party": "\u7121"
                }
            ],
            "totalVotables": 544,
            "voteRate": 73.71,
            "areaCode": null,
            "deptCode": "250"
        },
        "T3": {
            "candTksInfo": [
                {
                    "candNo": 1,
                    "tks": 0,
                    "candVictor": " ",
                    "tksRate": 0.0,
                    "name": "\u4f0d\u5b97\u5eb7",
                    "birthday": "19780723",
                    "party": "\u4e2d\u570b\u570b\u6c11\u9ee8"
                },
                {
                    "candNo": 2,
                    "tks": 0,
                    "candVictor": "*",
                    "tksRate": 0.0,
                    "name": "\u8c37\u66ae\u2027\u54c8\u5c31Kumu\u2027Hacyo",
                    "birthday": "19780528",
                    "party": "\u7121"
                }
            ],
            "totalVotables": 0,
            "voteRate": 0.0,
            "areaCode": "13",
            "deptCode": "250"
        },
        "F6": {
            "agreeTks": 152,
            "disagreeTks": 99,
            "totalVotables": 559,
            "voteRate": 49.37
        },
        "F7": {
            "agreeTks": 138,
            "disagreeTks": 123,
            "totalVotables": 559,
            "voteRate": 49.91
        },
        "F8": {
            "agreeTks": 69,
            "disagreeTks": 178,
            "totalVotables": 559,
            "voteRate": 49.37
        },
        "F9": {
            "agreeTks": 76,
            "disagreeTks": 170,
            "totalVotables": 559,
            "voteRate": 49.37
        },
        "F1": {
            "agreeTks": 196,
            "disagreeTks": 48,
            "totalVotables": 559,
            "voteRate": 49.02
        },
        "FA": {
            "agreeTks": 147,
            "disagreeTks": 89,
            "totalVotables": 559,
            "voteRate": 49.19
        },
        "F2": {
            "agreeTks": 185,
            "disagreeTks": 53,
            "totalVotables": 559,
            "voteRate": 49.02
        },
        "F3": {
            "agreeTks": 185,
            "disagreeTks": 57,
            "totalVotables": 559,
            "voteRate": 49.02
        },
        "F4": {
            "agreeTks": 210,
            "disagreeTks": 44,
            "totalVotables": 559,
            "voteRate": 49.55
        },
        "F5": {
            "agreeTks": 186,
            "disagreeTks": 68,
            "totalVotables": 559,
            "voteRate": 49.37
        },
        "age": [
            27,
            27,
            37,
            31,
            27,
            25,
            45,
            63,
            66,
            49,
            49,
            31,
            30,
            32,
            32,
            6,
            0,
            0
        ],
        "education": [
            212,
            147,
            137,
            28,
            48,
            4,
            1
        ],
        "sex": [
            320,
            257
        ],
        "merriage": [
            134,
            341,
            36,
            66
        ],
        "middle_num": 473
    },
    "007": {
        "T1": {
            "candTksInfo": [
                {
                    "candNo": 1,
                    "tks": 93,
                    "candVictor": " ",
                    "tksRate": 11.16,
                    "name": "\u8521\u7950\u660c",
                    "birthday": "19700112",
                    "party": "\u7121"
                },
                {
                    "candNo": 2,
                    "tks": 190,
                    "candVictor": " ",
                    "tksRate": 22.81,
                    "name": "\u9673\u798f\u6176",
                    "birthday": "19520625",
                    "party": "\u7121"
                },
                {
                    "candNo": 3,
                    "tks": 177,
                    "candVictor": " ",
                    "tksRate": 21.25,
                    "name": "\u738b\u958b\u73b9",
                    "birthday": "19820312",
                    "party": "\u6c11\u4e3b\u9032\u6b65\u9ee8"
                },
                {
                    "candNo": 4,
                    "tks": 373,
                    "candVictor": "*",
                    "tksRate": 44.78,
                    "name": "\u5468\u5955\u9f4a",
                    "birthday": "19881228",
                    "party": "\u7121"
                }
            ],
            "totalVotables": 1151,
            "voteRate": 73.68,
            "areaCode": "04",
            "deptCode": "250"
        },
        "T2": {
            "candTksInfo": [
                {
                    "candNo": 1,
                    "tks": 0,
                    "candVictor": "*",
                    "tksRate": 0.0,
                    "name": "\u7a4e\u827e\u9054\u5229 Ingay Tali",
                    "birthday": "19730306",
                    "party": "\u7121"
                },
                {
                    "candNo": 2,
                    "tks": 0,
                    "candVictor": " ",
                    "tksRate": 0.0,
                    "name": "\u7c21\u5fb7\u8f1d",
                    "birthday": "19610102",
                    "party": "\u4e2d\u570b\u570b\u6c11\u9ee8"
                },
                {
                    "candNo": 3,
                    "tks": 0,
                    "candVictor": " ",
                    "tksRate": 0.0,
                    "name": "\u674e\u7f8e\u7d20",
                    "birthday": "19690721",
                    "party": "\u6c11\u4e3b\u9032\u6b65\u9ee8"
                }
            ],
            "totalVotables": 1,
            "voteRate": 0.0,
            "areaCode": "12",
            "deptCode": "250"
        },
        "TC": {
            "candTksInfo": [
                {
                    "candNo": 1,
                    "tks": 251,
                    "candVictor": "*",
                    "tksRate": 30.2,
                    "name": "\u9ec3\u5049\u54f2",
                    "birthday": "19630926",
                    "party": "\u6c11\u4e3b\u9032\u6b65\u9ee8"
                },
                {
                    "candNo": 2,
                    "tks": 360,
                    "candVictor": " ",
                    "tksRate": 43.32,
                    "name": "\u9ad8\u601d\u535a",
                    "birthday": "19681031",
                    "party": "\u4e2d\u570b\u570b\u6c11\u9ee8"
                },
                {
                    "candNo": 3,
                    "tks": 82,
                    "candVictor": " ",
                    "tksRate": 9.87,
                    "name": "\u6797\u7fa9\u8c50",
                    "birthday": "19480204",
                    "party": "\u7121"
                },
                {
                    "candNo": 4,
                    "tks": 34,
                    "candVictor": " ",
                    "tksRate": 4.09,
                    "name": "\u8a31\u5fe0\u4fe1",
                    "birthday": "19650601",
                    "party": "\u7121"
                },
                {
                    "candNo": 5,
                    "tks": 65,
                    "candVictor": " ",
                    "tksRate": 7.82,
                    "name": "\u9673\u6c38\u548c",
                    "birthday": "19600216",
                    "party": "\u7121"
                },
                {
                    "candNo": 6,
                    "tks": 39,
                    "candVictor": " ",
                    "tksRate": 4.69,
                    "name": "\u8607\u7165\u667a",
                    "birthday": "19560720",
                    "party": "\u7121"
                }
            ],
            "totalVotables": 1158,
            "voteRate": 73.58,
            "areaCode": null,
            "deptCode": "250"
        },
        "T3": {
            "candTksInfo": [
                {
                    "candNo": 1,
                    "tks": 2,
                    "candVictor": " ",
                    "tksRate": 50.0,
                    "name": "\u4f0d\u5b97\u5eb7",
                    "birthday": "19780723",
                    "party": "\u4e2d\u570b\u570b\u6c11\u9ee8"
                },
                {
                    "candNo": 2,
                    "tks": 2,
                    "candVictor": "*",
                    "tksRate": 50.0,
                    "name": "\u8c37\u66ae\u2027\u54c8\u5c31Kumu\u2027Hacyo",
                    "birthday": "19780528",
                    "party": "\u7121"
                }
            ],
            "totalVotables": 6,
            "voteRate": 66.67,
            "areaCode": "13",
            "deptCode": "250"
        },
        "F6": {
            "agreeTks": 306,
            "disagreeTks": 196,
            "totalVotables": 1189,
            "voteRate": 44.91
        },
        "F7": {
            "agreeTks": 241,
            "disagreeTks": 264,
            "totalVotables": 1189,
            "voteRate": 43.99
        },
        "F8": {
            "agreeTks": 155,
            "disagreeTks": 349,
            "totalVotables": 1189,
            "voteRate": 44.41
        },
        "F9": {
            "agreeTks": 156,
            "disagreeTks": 335,
            "totalVotables": 1189,
            "voteRate": 44.07
        },
        "F1": {
            "agreeTks": 359,
            "disagreeTks": 84,
            "totalVotables": 1189,
            "voteRate": 39.36
        },
        "FA": {
            "agreeTks": 287,
            "disagreeTks": 165,
            "totalVotables": 1189,
            "voteRate": 40.62
        },
        "F2": {
            "agreeTks": 330,
            "disagreeTks": 106,
            "totalVotables": 1189,
            "voteRate": 39.28
        },
        "F3": {
            "agreeTks": 346,
            "disagreeTks": 98,
            "totalVotables": 1189,
            "voteRate": 39.44
        },
        "F4": {
            "agreeTks": 420,
            "disagreeTks": 105,
            "totalVotables": 1189,
            "voteRate": 44.66
        },
        "F5": {
            "agreeTks": 357,
            "disagreeTks": 154,
            "totalVotables": 1189,
            "voteRate": 44.74
        },
        "age": [
            65,
            87,
            89,
            69,
            100,
            104,
            86,
            99,
            106,
            105,
            102,
            62,
            66,
            55,
            27,
            7,
            1,
            1
        ],
        "education": [
            360,
            270,
            359,
            73,
            144,
            24,
            1
        ],
        "sex": [
            654,
            577
        ],
        "merriage": [
            349,
            666,
            103,
            113
        ],
        "middle_num": 541
    },
    "008": {
        "T1": {
            "candTksInfo": [
                {
                    "candNo": 1,
                    "tks": 28,
                    "candVictor": " ",
                    "tksRate": 3.4,
                    "name": "\u8521\u7950\u660c",
                    "birthday": "19700112",
                    "party": "\u7121"
                },
                {
                    "candNo": 2,
                    "tks": 332,
                    "candVictor": " ",
                    "tksRate": 40.34,
                    "name": "\u9673\u798f\u6176",
                    "birthday": "19520625",
                    "party": "\u7121"
                },
                {
                    "candNo": 3,
                    "tks": 123,
                    "candVictor": " ",
                    "tksRate": 14.95,
                    "name": "\u738b\u958b\u73b9",
                    "birthday": "19820312",
                    "party": "\u6c11\u4e3b\u9032\u6b65\u9ee8"
                },
                {
                    "candNo": 4,
                    "tks": 340,
                    "candVictor": "*",
                    "tksRate": 41.31,
                    "name": "\u5468\u5955\u9f4a",
                    "birthday": "19881228",
                    "party": "\u7121"
                }
            ],
            "totalVotables": 1015,
            "voteRate": 82.66,
            "areaCode": "04",
            "deptCode": "250"
        },
        "T2": {
            "candTksInfo": [
                {
                    "candNo": 1,
                    "tks": 0,
                    "candVictor": "*",
                    "tksRate": 0.0,
                    "name": "\u7a4e\u827e\u9054\u5229 Ingay Tali",
                    "birthday": "19730306",
                    "party": "\u7121"
                },
                {
                    "candNo": 2,
                    "tks": 0,
                    "candVictor": " ",
                    "tksRate": 0.0,
                    "name": "\u7c21\u5fb7\u8f1d",
                    "birthday": "19610102",
                    "party": "\u4e2d\u570b\u570b\u6c11\u9ee8"
                },
                {
                    "candNo": 3,
                    "tks": 0,
                    "candVictor": " ",
                    "tksRate": 0.0,
                    "name": "\u674e\u7f8e\u7d20",
                    "birthday": "19690721",
                    "party": "\u6c11\u4e3b\u9032\u6b65\u9ee8"
                }
            ],
            "totalVotables": 0,
            "voteRate": 0.0,
            "areaCode": "12",
            "deptCode": "250"
        },
        "TC": {
            "candTksInfo": [
                {
                    "candNo": 1,
                    "tks": 284,
                    "candVictor": "*",
                    "tksRate": 34.51,
                    "name": "\u9ec3\u5049\u54f2",
                    "birthday": "19630926",
                    "party": "\u6c11\u4e3b\u9032\u6b65\u9ee8"
                },
                {
                    "candNo": 2,
                    "tks": 288,
                    "candVictor": " ",
                    "tksRate": 34.99,
                    "name": "\u9ad8\u601d\u535a",
                    "birthday": "19681031",
                    "party": "\u4e2d\u570b\u570b\u6c11\u9ee8"
                },
                {
                    "candNo": 3,
                    "tks": 76,
                    "candVictor": " ",
                    "tksRate": 9.23,
                    "name": "\u6797\u7fa9\u8c50",
                    "birthday": "19480204",
                    "party": "\u7121"
                },
                {
                    "candNo": 4,
                    "tks": 17,
                    "candVictor": " ",
                    "tksRate": 2.07,
                    "name": "\u8a31\u5fe0\u4fe1",
                    "birthday": "19650601",
                    "party": "\u7121"
                },
                {
                    "candNo": 5,
                    "tks": 61,
                    "candVictor": " ",
                    "tksRate": 7.41,
                    "name": "\u9673\u6c38\u548c",
                    "birthday": "19600216",
                    "party": "\u7121"
                },
                {
                    "candNo": 6,
                    "tks": 97,
                    "candVictor": " ",
                    "tksRate": 11.79,
                    "name": "\u8607\u7165\u667a",
                    "birthday": "19560720",
                    "party": "\u7121"
                }
            ],
            "totalVotables": 1016,
            "voteRate": 82.38,
            "areaCode": null,
            "deptCode": "250"
        },
        "T3": {
            "candTksInfo": [
                {
                    "candNo": 1,
                    "tks": 0,
                    "candVictor": " ",
                    "tksRate": 0.0,
                    "name": "\u4f0d\u5b97\u5eb7",
                    "birthday": "19780723",
                    "party": "\u4e2d\u570b\u570b\u6c11\u9ee8"
                },
                {
                    "candNo": 2,
                    "tks": 0,
                    "candVictor": "*",
                    "tksRate": 0.0,
                    "name": "\u8c37\u66ae\u2027\u54c8\u5c31Kumu\u2027Hacyo",
                    "birthday": "19780528",
                    "party": "\u7121"
                }
            ],
            "totalVotables": 0,
            "voteRate": 0.0,
            "areaCode": "13",
            "deptCode": "250"
        },
        "F6": {
            "agreeTks": 340,
            "disagreeTks": 188,
            "totalVotables": 1044,
            "voteRate": 53.16
        },
        "F7": {
            "agreeTks": 224,
            "disagreeTks": 293,
            "totalVotables": 1044,
            "voteRate": 51.92
        },
        "F8": {
            "agreeTks": 135,
            "disagreeTks": 365,
            "totalVotables": 1044,
            "voteRate": 52.01
        },
        "F9": {
            "agreeTks": 143,
            "disagreeTks": 363,
            "totalVotables": 1044,
            "voteRate": 51.72
        },
        "F1": {
            "agreeTks": 381,
            "disagreeTks": 112,
            "totalVotables": 1044,
            "voteRate": 50.48
        },
        "FA": {
            "agreeTks": 270,
            "disagreeTks": 222,
            "totalVotables": 1044,
            "voteRate": 50.86
        },
        "F2": {
            "agreeTks": 371,
            "disagreeTks": 118,
            "totalVotables": 1044,
            "voteRate": 50.1
        },
        "F3": {
            "agreeTks": 361,
            "disagreeTks": 130,
            "totalVotables": 1044,
            "voteRate": 50.38
        },
        "F4": {
            "agreeTks": 418,
            "disagreeTks": 108,
            "totalVotables": 1044,
            "voteRate": 52.49
        },
        "F5": {
            "agreeTks": 379,
            "disagreeTks": 147,
            "totalVotables": 1044,
            "voteRate": 52.68
        },
        "age": [
            61,
            71,
            93,
            63,
            85,
            94,
            89,
            106,
            99,
            93,
            80,
            51,
            40,
            30,
            17,
            7,
            1,
            0
        ],
        "education": [
            334,
            249,
            304,
            46,
            132,
            12,
            3
        ],
        "sex": [
            568,
            512
        ],
        "merriage": [
            323,
            575,
            91,
            91
        ],
        "middle_num": 518
    },
    "009": {
        "T1": {
            "candTksInfo": [
                {
                    "candNo": 1,
                    "tks": 128,
                    "candVictor": " ",
                    "tksRate": 20.06,
                    "name": "\u8521\u7950\u660c",
                    "birthday": "19700112",
                    "party": "\u7121"
                },
                {
                    "candNo": 2,
                    "tks": 182,
                    "candVictor": " ",
                    "tksRate": 28.53,
                    "name": "\u9673\u798f\u6176",
                    "birthday": "19520625",
                    "party": "\u7121"
                },
                {
                    "candNo": 3,
                    "tks": 79,
                    "candVictor": " ",
                    "tksRate": 12.38,
                    "name": "\u738b\u958b\u73b9",
                    "birthday": "19820312",
                    "party": "\u6c11\u4e3b\u9032\u6b65\u9ee8"
                },
                {
                    "candNo": 4,
                    "tks": 249,
                    "candVictor": "*",
                    "tksRate": 39.03,
                    "name": "\u5468\u5955\u9f4a",
                    "birthday": "19881228",
                    "party": "\u7121"
                }
            ],
            "totalVotables": 904,
            "voteRate": 71.9,
            "areaCode": "04",
            "deptCode": "250"
        },
        "T2": {
            "candTksInfo": [
                {
                    "candNo": 1,
                    "tks": 0,
                    "candVictor": "*",
                    "tksRate": 0.0,
                    "name": "\u7a4e\u827e\u9054\u5229 Ingay Tali",
                    "birthday": "19730306",
                    "party": "\u7121"
                },
                {
                    "candNo": 2,
                    "tks": 0,
                    "candVictor": " ",
                    "tksRate": 0.0,
                    "name": "\u7c21\u5fb7\u8f1d",
                    "birthday": "19610102",
                    "party": "\u4e2d\u570b\u570b\u6c11\u9ee8"
                },
                {
                    "candNo": 3,
                    "tks": 0,
                    "candVictor": " ",
                    "tksRate": 0.0,
                    "name": "\u674e\u7f8e\u7d20",
                    "birthday": "19690721",
                    "party": "\u6c11\u4e3b\u9032\u6b65\u9ee8"
                }
            ],
            "totalVotables": 0,
            "voteRate": 0.0,
            "areaCode": "12",
            "deptCode": "250"
        },
        "TC": {
            "candTksInfo": [
                {
                    "candNo": 1,
                    "tks": 164,
                    "candVictor": "*",
                    "tksRate": 25.63,
                    "name": "\u9ec3\u5049\u54f2",
                    "birthday": "19630926",
                    "party": "\u6c11\u4e3b\u9032\u6b65\u9ee8"
                },
                {
                    "candNo": 2,
                    "tks": 325,
                    "candVictor": " ",
                    "tksRate": 50.78,
                    "name": "\u9ad8\u601d\u535a",
                    "birthday": "19681031",
                    "party": "\u4e2d\u570b\u570b\u6c11\u9ee8"
                },
                {
                    "candNo": 3,
                    "tks": 59,
                    "candVictor": " ",
                    "tksRate": 9.22,
                    "name": "\u6797\u7fa9\u8c50",
                    "birthday": "19480204",
                    "party": "\u7121"
                },
                {
                    "candNo": 4,
                    "tks": 16,
                    "candVictor": " ",
                    "tksRate": 2.5,
                    "name": "\u8a31\u5fe0\u4fe1",
                    "birthday": "19650601",
                    "party": "\u7121"
                },
                {
                    "candNo": 5,
                    "tks": 42,
                    "candVictor": " ",
                    "tksRate": 6.56,
                    "name": "\u9673\u6c38\u548c",
                    "birthday": "19600216",
                    "party": "\u7121"
                },
                {
                    "candNo": 6,
                    "tks": 34,
                    "candVictor": " ",
                    "tksRate": 5.31,
                    "name": "\u8607\u7165\u667a",
                    "birthday": "19560720",
                    "party": "\u7121"
                }
            ],
            "totalVotables": 913,
            "voteRate": 71.96,
            "areaCode": null,
            "deptCode": "250"
        },
        "T3": {
            "candTksInfo": [
                {
                    "candNo": 1,
                    "tks": 0,
                    "candVictor": " ",
                    "tksRate": 0.0,
                    "name": "\u4f0d\u5b97\u5eb7",
                    "birthday": "19780723",
                    "party": "\u4e2d\u570b\u570b\u6c11\u9ee8"
                },
                {
                    "candNo": 2,
                    "tks": 6,
                    "candVictor": "*",
                    "tksRate": 100.0,
                    "name": "\u8c37\u66ae\u2027\u54c8\u5c31Kumu\u2027Hacyo",
                    "birthday": "19780528",
                    "party": "\u7121"
                }
            ],
            "totalVotables": 7,
            "voteRate": 85.71,
            "areaCode": "13",
            "deptCode": "250"
        },
        "F6": {
            "agreeTks": 302,
            "disagreeTks": 158,
            "totalVotables": 941,
            "voteRate": 52.18
        },
        "F7": {
            "agreeTks": 200,
            "disagreeTks": 261,
            "totalVotables": 941,
            "voteRate": 51.97
        },
        "F8": {
            "agreeTks": 123,
            "disagreeTks": 334,
            "totalVotables": 941,
            "voteRate": 51.65
        },
        "F9": {
            "agreeTks": 125,
            "disagreeTks": 340,
            "totalVotables": 941,
            "voteRate": 51.75
        },
        "F1": {
            "agreeTks": 369,
            "disagreeTks": 92,
            "totalVotables": 941,
            "voteRate": 51.86
        },
        "FA": {
            "agreeTks": 257,
            "disagreeTks": 198,
            "totalVotables": 941,
            "voteRate": 51.65
        },
        "F2": {
            "agreeTks": 356,
            "disagreeTks": 104,
            "totalVotables": 941,
            "voteRate": 51.86
        },
        "F3": {
            "agreeTks": 376,
            "disagreeTks": 91,
            "totalVotables": 941,
            "voteRate": 51.86
        },
        "F4": {
            "agreeTks": 380,
            "disagreeTks": 98,
            "totalVotables": 941,
            "voteRate": 52.07
        },
        "F5": {
            "agreeTks": 341,
            "disagreeTks": 122,
            "totalVotables": 941,
            "voteRate": 51.97
        },
        "age": [
            77,
            86,
            89,
            93,
            96,
            70,
            85,
            83,
            80,
            72,
            47,
            32,
            28,
            21,
            11,
            2,
            1,
            0
        ],
        "education": [
            250,
            258,
            294,
            44,
            116,
            11,
            0
        ],
        "sex": [
            497,
            476
        ],
        "merriage": [
            299,
            523,
            81,
            70
        ],
        "middle_num": 532
    }
}