{
    "T1": {
        "candTksInfo": [
            {
                "candNo": 1,
                "tks": 5793,
                "candVictor": "*",
                "tksRate": 21.73,
                "name": "\u90b1\u4fca\u61b2",
                "birthday": "19820226",
                "party": "\u6c11\u4e3b\u9032\u6b65\u9ee8"
            },
            {
                "candNo": 2,
                "tks": 1261,
                "candVictor": "*",
                "tksRate": 4.73,
                "name": "\u6c5f\u745e\u9d3b",
                "birthday": "19640214",
                "party": "\u6c11\u4e3b\u9032\u6b65\u9ee8"
            },
            {
                "candNo": 3,
                "tks": 2530,
                "candVictor": "*",
                "tksRate": 9.49,
                "name": "\u5f35\u52dd\u5bcc",
                "birthday": "19721007",
                "party": "\u6c11\u4e3b\u9032\u6b65\u9ee8"
            },
            {
                "candNo": 4,
                "tks": 3070,
                "candVictor": " ",
                "tksRate": 11.51,
                "name": "\u9673\u6e05\u8302",
                "birthday": "19721022",
                "party": "\u7121"
            },
            {
                "candNo": 5,
                "tks": 1858,
                "candVictor": " ",
                "tksRate": 6.97,
                "name": "\u694a\u7389\u4ed9",
                "birthday": "19870623",
                "party": "\u7121"
            },
            {
                "candNo": 6,
                "tks": 2573,
                "candVictor": " ",
                "tksRate": 9.65,
                "name": "\u6797\u82b3\u5982",
                "birthday": "19680111",
                "party": "\u6c11\u4e3b\u9032\u6b65\u9ee8"
            },
            {
                "candNo": 7,
                "tks": 139,
                "candVictor": " ",
                "tksRate": 0.52,
                "name": "\u674e\u4fca\u5fb7",
                "birthday": "19691008",
                "party": "\u7121"
            },
            {
                "candNo": 8,
                "tks": 3684,
                "candVictor": "*",
                "tksRate": 13.82,
                "name": "\u5433\u5229\u6210",
                "birthday": "19691108",
                "party": "\u4e2d\u570b\u570b\u6c11\u9ee8"
            },
            {
                "candNo": 9,
                "tks": 794,
                "candVictor": " ",
                "tksRate": 2.98,
                "name": "\u4f55\u5805\u5fc3",
                "birthday": "19471014",
                "party": "\u7121"
            },
            {
                "candNo": 10,
                "tks": 4959,
                "candVictor": "*",
                "tksRate": 18.6,
                "name": "\u8a31\u6167\u7389",
                "birthday": "19670222",
                "party": "\u4e2d\u570b\u570b\u6c11\u9ee8"
            }
        ],
        "totalVotables": 37702,
        "voteRate": 73.19,
        "areaCode": "05",
        "deptCode": "180"
    },
    "T2": {
        "candTksInfo": [
            {
                "candNo": 1,
                "tks": 33,
                "candVictor": " ",
                "tksRate": 67.35,
                "name": "\u4fc4\u9127\uff0e\u6bb7\u827e Eteng\uff0eIngay",
                "birthday": "19650224",
                "party": "\u6c11\u4e3b\u9032\u6b65\u9ee8"
            },
            {
                "candNo": 2,
                "tks": 12,
                "candVictor": "*",
                "tksRate": 24.49,
                "name": "\u738b\u7fa9\u96c4",
                "birthday": "19600320",
                "party": "\u4e2d\u570b\u570b\u6c11\u9ee8"
            },
            {
                "candNo": 3,
                "tks": 4,
                "candVictor": " ",
                "tksRate": 8.16,
                "name": "\u8a79\u91d1\u798f",
                "birthday": "19490408",
                "party": "\u89aa\u6c11\u9ee8"
            }
        ],
        "totalVotables": 80,
        "voteRate": 67.5,
        "areaCode": "12",
        "deptCode": "180"
    },
    "TC": {
        "candTksInfo": [
            {
                "candNo": 1,
                "tks": 14410,
                "candVictor": "*",
                "tksRate": 52.23,
                "name": "\u97d3\u570b\u745c",
                "birthday": "19570617",
                "party": "\u4e2d\u570b\u570b\u6c11\u9ee8"
            },
            {
                "candNo": 2,
                "tks": 12806,
                "candVictor": " ",
                "tksRate": 46.42,
                "name": "\u9673\u5176\u9081",
                "birthday": "19641223",
                "party": "\u6c11\u4e3b\u9032\u6b65\u9ee8"
            },
            {
                "candNo": 3,
                "tks": 115,
                "candVictor": " ",
                "tksRate": 0.42,
                "name": "\u74a9\u7f8e\u9cf3",
                "birthday": "19660805",
                "party": "\u7121"
            },
            {
                "candNo": 4,
                "tks": 258,
                "candVictor": " ",
                "tksRate": 0.94,
                "name": "\u8607\u76c8\u8cb4",
                "birthday": "19581007",
                "party": "\u7121"
            }
        ],
        "totalVotables": 38116,
        "voteRate": 73.2,
        "areaCode": null,
        "deptCode": "180"
    },
    "T3": {
        "candTksInfo": [
            {
                "candNo": 1,
                "tks": 26,
                "candVictor": " ",
                "tksRate": 49.06,
                "name": "\u8303\u7e54\u6b3d Pasulang\uff0eTomatalate",
                "birthday": "19570729",
                "party": "\u7121"
            },
            {
                "candNo": 2,
                "tks": 27,
                "candVictor": "*",
                "tksRate": 50.94,
                "name": "\u5510\u60e0\u7f8e",
                "birthday": "19580101",
                "party": "\u4e2d\u570b\u570b\u6c11\u9ee8"
            }
        ],
        "totalVotables": 81,
        "voteRate": 69.14,
        "areaCode": "15",
        "deptCode": "180"
    },
    "F6": {
        "agreeTks": 14437,
        "disagreeTks": 8605,
        "totalVotables": 39191,
        "voteRate": 58.79
    },
    "F7": {
        "agreeTks": 11883,
        "disagreeTks": 11317,
        "totalVotables": 39191,
        "voteRate": 59.2
    },
    "F8": {
        "agreeTks": 7872,
        "disagreeTks": 14815,
        "totalVotables": 39191,
        "voteRate": 57.89
    },
    "F9": {
        "agreeTks": 7877,
        "disagreeTks": 14661,
        "totalVotables": 39191,
        "voteRate": 57.51
    },
    "F1": {
        "agreeTks": 16980,
        "disagreeTks": 4996,
        "totalVotables": 39191,
        "voteRate": 56.07
    },
    "FA": {
        "agreeTks": 12625,
        "disagreeTks": 9306,
        "totalVotables": 39191,
        "voteRate": 55.96
    },
    "F2": {
        "agreeTks": 16185,
        "disagreeTks": 5680,
        "totalVotables": 39191,
        "voteRate": 55.79
    },
    "F3": {
        "agreeTks": 16620,
        "disagreeTks": 5282,
        "totalVotables": 39191,
        "voteRate": 55.89
    },
    "F4": {
        "agreeTks": 16980,
        "disagreeTks": 6317,
        "totalVotables": 39191,
        "voteRate": 59.44
    },
    "F5": {
        "agreeTks": 15786,
        "disagreeTks": 7300,
        "totalVotables": 39191,
        "voteRate": 58.91
    },
    "age": [
        2227,
        3146,
        3282,
        3215,
        3633,
        3301,
        3315,
        3740,
        4067,
        3847,
        2927,
        1402,
        1050,
        644,
        320,
        155,
        25,
        6
    ],
    "education": [
        4947,
        5507,
        12964,
        4158,
        9745,
        2652,
        329
    ],
    "sex": [
        20339,
        19963
    ],
    "merriage": [
        13690,
        20896,
        3424,
        2292
    ],
    "middle_num": 688
}